llama_index/embeddings/__init__.py
llama_index/embeddings/openai/__init__.py
llama_index/embeddings/openai/base.py
llama_index/embeddings/openai/utils.py
llama_index_embeddings_openai-0.2.2.dist-info/METADATA
llama_index_embeddings_openai-0.2.2.dist-info/WHEEL
llama_index_embeddings_openai-0.2.2.dist-info/RECORD
