Metadata-Version: 2.1
Name: llama-index-embeddings-openai
Version: 0.2.2
Summary: llama-index embeddings openai integration
License: MIT
Author: Your Name
Author-email: you@example.com
Requires-Python: >=3.8.1,<4.0
Classifier: License :: OSI Approved :: MIT License
Classifier: Programming Language :: Python :: 3
Classifier: Programming Language :: Python :: 3.9
Classifier: Programming Language :: Python :: 3.10
Classifier: Programming Language :: Python :: 3.11
Classifier: Programming Language :: Python :: 3.12
Requires-Dist: llama-index-core (>=0.11.0,<0.12.0)
Requires-Dist: openai (>=1.1.0)
